test_ddyss_mcp_demo/__init__.py
test_ddyss_mcp_demo-0.1.0.dist-info/METADATA
test_ddyss_mcp_demo-0.1.0.dist-info/WHEEL
test_ddyss_mcp_demo-0.1.0.dist-info/entry_points.txt
test_ddyss_mcp_demo-0.1.0.dist-info/RECORD
