Metadata-Version: 2.4
Name: test-ddyss-mcp-demo
Version: 0.1.0
Summary: Add your description here
Requires-Python: >=3.12
Requires-Dist: mcp[cli]>=1.9.3
